askpandas/__init__.py
askpandas/core/__init__.py
askpandas/core/dataframe.py
askpandas/core/engine.py
askpandas/core/query_processor.py
askpandas/llm/__init__.py
askpandas/llm/base.py
askpandas/llm/huggingface_client.py
askpandas/llm/ollama_client.py
askpandas/security/__init__.py
askpandas/security/sandbox.py
askpandas/utils/__init__.py
askpandas/utils/data_quality.py
askpandas/utils/helpers.py
askpandas/utils/performance.py
askpandas/utils/statistical.py
askpandas/visualization/__init__.py
askpandas/visualization/charts.py
askpandas-0.1.1.dist-info/licenses/LICENSE
tests/__init__.py
tests/test_dataframe.py
askpandas-0.1.1.dist-info/METADATA
askpandas-0.1.1.dist-info/WHEEL
askpandas-0.1.1.dist-info/top_level.txt
askpandas-0.1.1.dist-info/RECORD
