Metadata-Version: 2.4
Name: askpandas
Version: 0.1.1
Summary: AI-powered data engineering and analytics assistant for querying CSV data using natural language—locally and intelligently
Home-page: https://github.com/irfanalidv/AskPandas
Author: Md Irfan Ali
Author-email: irfanali29@hotmail.com
Project-URL: Bug Reports, https://github.com/irfanalidv/AskPandas/issues
Project-URL: Source, https://github.com/irfanalidv/AskPandas
Project-URL: Documentation, https://github.com/irfanalidv/AskPandas#readme
Keywords: data-analysis,pandas,ai,natural-language,csv,data-science,machine-learning,llm,ollama,huggingface
Classifier: Development Status :: 3 - Alpha
Classifier: Intended Audience :: Developers
Classifier: Intended Audience :: Science/Research
Classifier: License :: OSI Approved :: MIT License
Classifier: Programming Language :: Python :: 3.8
Classifier: Programming Language :: Python :: 3.9
Classifier: Programming Language :: Python :: 3.10
Classifier: Programming Language :: Python :: 3.11
Classifier: Programming Language :: Python :: 3.12
Classifier: Topic :: Scientific/Engineering :: Information Analysis
Classifier: Topic :: Software Development :: Libraries :: Python Modules
Classifier: Topic :: Text Processing :: Linguistic
Classifier: Topic :: Scientific/Engineering :: Artificial Intelligence
Requires-Python: >=3.8
License-File: LICENSE
Requires-Dist: pandas>=1.5.0
Requires-Dist: numpy>=1.23.0
Requires-Dist: matplotlib>=3.5.0
Requires-Dist: seaborn>=0.12.0
Requires-Dist: requests>=2.28.0
Requires-Dist: transformers>=4.30.0
Requires-Dist: torch>=2.0.0
Requires-Dist: faker>=18.0.0
Provides-Extra: dev
Requires-Dist: pytest>=7.0.0; extra == "dev"
Requires-Dist: pytest-cov>=4.0.0; extra == "dev"
Requires-Dist: black>=22.0.0; extra == "dev"
Requires-Dist: flake8>=5.0.0; extra == "dev"
Requires-Dist: mypy>=1.0.0; extra == "dev"
Provides-Extra: full
Requires-Dist: jupyter>=1.0.0; extra == "full"
Requires-Dist: ipywidgets>=8.0.0; extra == "full"
Requires-Dist: plotly>=5.0.0; extra == "full"
Requires-Dist: bokeh>=3.0.0; extra == "full"
Dynamic: author
Dynamic: author-email
Dynamic: classifier
Dynamic: description
Dynamic: description-content-type
Dynamic: home-page
Dynamic: keywords
Dynamic: license-file
Dynamic: project-url
Dynamic: provides-extra
Dynamic: requires-dist
Dynamic: requires-python
Dynamic: summary
